db_mysql_tool/__init__.py
db_mysql_tool/cli.py
db_mysql_tool/mysql_utils.py
db_mysql_tool-0.1.1.dist-info/licenses/LICENSE
db_mysql_tool-0.1.1.dist-info/METADATA
db_mysql_tool-0.1.1.dist-info/WHEEL
db_mysql_tool-0.1.1.dist-info/entry_points.txt
db_mysql_tool-0.1.1.dist-info/top_level.txt
db_mysql_tool-0.1.1.dist-info/RECORD
