Metadata-Version: 2.4
Name: db-mysql-tool
Version: 0.1.1
Summary: A well-encapsulated Python class tool for MySQL database operations
Author-email: Xiyangui <15243228311@163.com>
License: MIT
Project-URL: Homepage, https://github.com/yourusername/my-mysql-tool
Project-URL: Documentation, https://github.com/yourusername/my-mysql-tool#readme
Project-URL: Issues, https://github.com/yourusername/my-mysql-tool/issues
Project-URL: Source, https://github.com/yourusername/my-mysql-tool
Keywords: mysql,database,orm,pymysql,database-tool
Classifier: Development Status :: 4 - Beta
Classifier: Intended Audience :: Developers
Classifier: License :: OSI Approved :: MIT License
Classifier: Operating System :: OS Independent
Classifier: Programming Language :: Python :: 3
Classifier: Programming Language :: Python :: 3.7
Classifier: Programming Language :: Python :: 3.8
Classifier: Programming Language :: Python :: 3.9
Classifier: Programming Language :: Python :: 3.10
Classifier: Programming Language :: Python :: 3.11
Classifier: Programming Language :: Python :: 3.12
Classifier: Programming Language :: Python :: 3.13
Classifier: Topic :: Database
Classifier: Topic :: Software Development :: Libraries :: Python Modules
Requires-Python: >=3.7
License-File: LICENSE
Requires-Dist: pymysql>=1.1.2
Provides-Extra: dev
Requires-Dist: pytest>=6.0; extra == "dev"
Requires-Dist: pytest-cov; extra == "dev"
Requires-Dist: black; extra == "dev"
Requires-Dist: flake8; extra == "dev"
Requires-Dist: mypy; extra == "dev"
Dynamic: license-file
